structlog_to_seq/__init__.py
structlog_to_seq/abs_processor.py
structlog_to_seq/celf_processor.py
structlog_to_seq/message_template_renderer.py
structlog_to_seq-21.0.0.dist-info/LICENSE
structlog_to_seq-21.0.0.dist-info/WHEEL
structlog_to_seq-21.0.0.dist-info/METADATA
structlog_to_seq-21.0.0.dist-info/RECORD
